bits/__init__.py
bits/proftpd/__init__.py
bits_proftpd-1.0.1.dist-info/METADATA
bits_proftpd-1.0.1.dist-info/WHEEL
bits_proftpd-1.0.1.dist-info/top_level.txt
bits_proftpd-1.0.1.dist-info/RECORD
